tucan/__init__.py
tucan/clean_ifdef.py
tucan/cli.py
tucan/cli_pprinter.py
tucan/complexities.py
tucan/guess_language.py
tucan/imports_c.py
tucan/imports_common.py
tucan/imports_ftn.py
tucan/imports_main.py
tucan/imports_py.py
tucan/kw_lang.py
tucan/package_analysis.py
tucan/string_utils.py
tucan/struct_c.py
tucan/struct_common.py
tucan/struct_ftn.py
tucan/struct_main.py
tucan/struct_py.py
tucan/supported_files.py
tucan/travel_in_package.py
tucan/tucanexceptions.py
tucan/tucanlogging.py
tucan/unformat_c.py
tucan/unformat_common.py
tucan/unformat_ftn.py
tucan/unformat_main.py
tucan/unformat_py.py
tucan-0.5.0.dist-info/LICENSE.txt
tucan-0.5.0.dist-info/METADATA
tucan-0.5.0.dist-info/WHEEL
tucan-0.5.0.dist-info/entry_points.txt
tucan-0.5.0.dist-info/top_level.txt
tucan-0.5.0.dist-info/RECORD
