Metadata-Version: 2.1
Name: tucan
Version: 0.5.0
Summary: Unformatter Tool to allow parsing and analysis of code base.
Home-page: https://gitlab.com/cerfacs/tucan
Author: Antoine Dauptain, Thibault Marzlin, CoopTeam-CERFACS
Author-email: coop@cerfacs.fr
Project-URL: Homepage, https://gitlab.com/cerfacs/tucan
Project-URL: Documentation, https://tucan.readthedocs.io/en/latest/
Project-URL: Bug Tracker, https://gitlab.com/cerfacs/tucan/-/issues
Keywords: code,fortran,python
Classifier: Programming Language :: Python :: 3.8
Classifier: Programming Language :: Python :: 3.9
Classifier: Programming Language :: Python :: 3.10
Classifier: License :: OSI Approved :: MIT License
Requires-Python: >=3.8
License-File: LICENSE.txt
Requires-Dist: click
Requires-Dist: loguru
Provides-Extra: docs
Requires-Dist: sphinx-rtd-theme ; extra == 'docs'
Requires-Dist: recommonmark ; extra == 'docs'
Provides-Extra: tests
Requires-Dist: pytest ; extra == 'tests'
Requires-Dist: pytest-coverage ; extra == 'tests'
Requires-Dist: pytest-allclose ; extra == 'tests'
